LICENSE.txt
MANIFEST.in
README.rst
setup.py
chalk/__init__.py
chalk/__init__.pyc
chalk/admin.py
chalk/admin.pyc
chalk/feeds.py
chalk/feeds.pyc
chalk/models.py
chalk/models.pyc
chalk/settings.py
chalk/settings.pyc
chalk/test_urls.pyc
chalk/tests.py
chalk/tests.pyc
chalk/urls.py
chalk/urls.pyc
chalk/views.py
chalk/views.pyc
chalk/fixtures/chalk_test_data.json
chalk/migrations/0001_initial.py
chalk/migrations/0001_initial.pyc
chalk/migrations/0002_add_field_article_meta_description.py
chalk/migrations/0002_add_field_article_meta_description.pyc
chalk/migrations/__init__.py
chalk/migrations/__init__.pyc
chalk/templates/chalk/article_detail.html
chalk/templates/chalk/article_list.html
chalk/templates/chalk/feed_list.html
django_chalk.egg-info/PKG-INFO
django_chalk.egg-info/SOURCES.txt
django_chalk.egg-info/dependency_links.txt
django_chalk.egg-info/not-zip-safe
django_chalk.egg-info/requires.txt
django_chalk.egg-info/top_level.txt