Metadata-Version: 1.1
Name: django-chalk
Version: 0.2.1
Summary: Simple reStructuredText blogging for Django
Home-page: http://kevindias.com/projects/chalk/
Author: Kevin Dias
Author-email: kevin@kevindias.com
License: UNKNOWN
Platform: UNKNOWN
Classifier: Development Status :: 3 - Alpha
Classifier: Environment :: Web Environment
Classifier: Intended Audience :: Developers
Classifier: License :: OSI Approved :: BSD License
Classifier: Operating System :: OS Independent
Classifier: Programming Language :: Python
Classifier: Framework :: Django
Classifier: Topic :: Utilities
